python_vuejs/__init__.py
python_vuejs/cli.py
python_vuejs/django.py
python_vuejs/utils.py
python_vuejs/vuejs.py
python_vuejs-1.0.9.dist-info/DESCRIPTION.rst
python_vuejs-1.0.9.dist-info/METADATA
python_vuejs-1.0.9.dist-info/RECORD
python_vuejs-1.0.9.dist-info/WHEEL
python_vuejs-1.0.9.dist-info/entry_points.txt
python_vuejs-1.0.9.dist-info/metadata.json
python_vuejs-1.0.9.dist-info/top_level.txt
