Metadata-Version: 1.1
Name: python_vuejs
Version: 1.0.9
Summary: Gluing Python and Vue.js with a set of scripts in order to automate project and app builds
Home-page: https://github.com/cstrap/python-vuejs
Author: Christian Strappazzon
Author-email: lab@strap.it
License: MIT license
Keywords: python_vuejs
Platform: UNKNOWN
Classifier: Development Status :: 5 - Production/Stable
Classifier: Environment :: Web Environment
Classifier: Intended Audience :: Developers
Classifier: License :: OSI Approved :: MIT License
Classifier: Natural Language :: English
Classifier: Programming Language :: Python :: 2
Classifier: Programming Language :: Python :: 2.7
Classifier: Programming Language :: Python :: 3
Classifier: Programming Language :: Python :: 3.4
Classifier: Programming Language :: Python :: 3.5
Classifier: Programming Language :: Python :: 3.6
Classifier: Topic :: Software Development :: Libraries :: Python Modules
